pyams_mail/__init__.py
pyams_mail/include.py
pyams_mail/interfaces.py
pyams_mail/mailer.py
pyams_mail/message.py
pyams_mail/doctests/README.rst
pyams_mail/locales/pyams_mail.pot
pyams_mail/locales/fr/LC_MESSAGES/pyams_mail.po
pyams_mail/tests/__init__.py
pyams_mail/tests/test_utilsdocs.py
pyams_mail/tests/test_utilsdocstrings.py
pyams_mail-2.0.1.dist-info/LICENSE
pyams_mail-2.0.1.dist-info/METADATA
pyams_mail-2.0.1.dist-info/WHEEL
pyams_mail-2.0.1.dist-info/namespace_packages.txt
pyams_mail-2.0.1.dist-info/top_level.txt
pyams_mail-2.0.1.dist-info/RECORD
