Metadata-Version: 2.1
Name: pyams-mail
Version: 2.0.1
Summary: PyAMS mailing helper package
Home-page: https://pyams.readthedocs.io
Author: Thierry Florac
Author-email: tflorac@ulthar.net
License: ZPL
Keywords: Pyramid PyAMS
Classifier: License :: OSI Approved :: Zope Public License
Classifier: Development Status :: 4 - Beta
Classifier: Programming Language :: Python
Classifier: Framework :: Pyramid
Classifier: Topic :: Software Development :: Libraries :: Python Modules
Requires-Python: >=3.7
License-File: LICENSE
Requires-Dist: setuptools
Requires-Dist: pyams-utils
Requires-Dist: pyramid
Requires-Dist: pyramid-mailer
Requires-Dist: zope.componentvocabulary
Requires-Dist: zope.interface
Provides-Extra: test
